py_liant/__init__.py
py_liant/__version__.py
py_liant/enum.py
py_liant/interfaces.py
py_liant/json_decoder.py
py_liant/json_encoder.py
py_liant/json_object.py
py_liant/monkeypatch.py
py_liant/parser.py
py_liant/pyramid.py
py_liant/searchpath.py
py_liant/tests/__init__.py
py_liant/tests/test.py
py_liant/tests/models/__init__.py
py_liant-0.8.7.dist-info/LICENSE
py_liant-0.8.7.dist-info/METADATA
py_liant-0.8.7.dist-info/WHEEL
py_liant-0.8.7.dist-info/top_level.txt
py_liant-0.8.7.dist-info/RECORD
