Metadata-Version: 2.1
Name: py-liant
Version: 0.8.7
Summary: Glue together pyramid, sqlalchemy, simplejson to provide a read-write, object-graph-aware JSON API
Home-page: https://github.com/tripsolutions/py-liant
Author: George Barbăroșie
Author-email: george.barbarosie@gmail.com
License: MIT
Platform: UNKNOWN
Classifier: License :: OSI Approved :: MIT License
Classifier: Programming Language :: Python
Classifier: Programming Language :: Python :: 3
Classifier: Programming Language :: Python :: 3.4
Classifier: Programming Language :: Python :: Implementation :: CPython
Classifier: Programming Language :: Python :: Implementation :: PyPy
Requires-Python: >=3.4.0
Requires-Dist: SQLAlchemy
Requires-Dist: isodate
Requires-Dist: pyparsing
Requires-Dist: pyramid
Requires-Dist: python-dateutil
Requires-Dist: simplejson
Requires-Dist: transaction
